<?xml version="1.0" encoding="UTF-8"?>
<prefab>
    <property name="CopyAirBlocks" value="False" />
    <property name="AllowTopSoilDecorations" value="False" />
    <property name="YOffset" value="-10" />
    <property name="RotationToFaceNorth" value="0" />
    <property name="Zoning" value="Commercial" />
    <property name="AllowedTownships" value="city" />
    <property name="AllowedBiomes" value="wasteland_hub" />
    <property name="StaticSpawner.Class" value="SpawnMedium" />
    <property name="StaticSpawner.Size" value="32,2,32" />
    <property name="StaticSpawner.Trigger" value="160" />
    <property name="MaxPerHub" value="1" />
</prefab>
